LICENSE
README.md
setup.cfg
setup.py
user_utils/__init__.py
user_utils/__main__.py
user_utils/colors.py
user_utils/commands.py
user_utils/distro_release.py
user_utils/userconf.py
user_utils.egg-info/PKG-INFO
user_utils.egg-info/SOURCES.txt
user_utils.egg-info/dependency_links.txt
user_utils.egg-info/not-zip-safe
user_utils.egg-info/top_level.txt